cpi/__init__.py
cpi/livecpi.py
livecpi-0.1.2.data/scripts/livecpi
livecpi-0.1.2.dist-info/METADATA
livecpi-0.1.2.dist-info/WHEEL
livecpi-0.1.2.dist-info/top_level.txt
livecpi-0.1.2.dist-info/RECORD
