Metadata-Version: 2.1
Name: livecpi
Version: 0.1.2
Summary: Calculates Pi using different methods
Home-page: https://github.com/MatthyPlayz/LiveCPi
Author: Christian Matthy
Author-email: cjmatthy200@gmail.com
License: UNKNOWN
Platform: UNKNOWN
Classifier: Programming Language :: Python :: 3
Classifier: Operating System :: OS Independent
